{
  "openapi": "3.0.0",
  "info": {
    "title": "API de Señaventura",
    "version": "1.0.0",
    "description": ""
  },
  "servers": [
    {
      "url": "http://localhost:3000/"
    }
  ],
  "paths": {
    "/niveles/": {
      "get": {
        "tags": [
          "Niveles"
        ],
        "description": "Endpoint para obtener todos los niveles.",
        "responses": {
          "200": {
            "description": "Niveles obtenidos correctamente.",
            "content": {
              "application/json": {
                "schema": {
                  "type": "array",
                  "items": {
                    "type": "object",
                    "properties": {
                      "id_nivel": {
                        "type": "integer"
                      },
                      "id_isla": {
                        "type": "integer"
                      },
                      "nombre": {
                        "type": "string"
                      }
                    }
                  }
                }
              }
            }
          },
          "500": {
            "description": "Error al obtener los niveles.",
            "content": {
              "application/json": {
                "schema": {
                  "type": "object",
                  "properties": {
                    "error": {
                      "type": "string"
                    }
                  }
                }
              }
            }
          }
        }
      },
      "post": {
        "tags": [
          "Niveles"
        ],
        "description": "Endpoint para crear un nuevo nivel.",
        "responses": {
          "200": {
            "description": "Nivel creado correctamente.",
            "content": {
              "application/json": {
                "schema": {
                  "type": "object",
                  "properties": {
                    "id_nivel": {
                      "type": "integer"
                    },
                    "id_isla": {
                      "type": "integer"
                    },
                    "nombre": {
                      "type": "string"
                    }
                  }
                }
              }
            }
          },
          "500": {
            "description": "Error al crear el nivel.",
            "content": {
              "application/json": {
                "schema": {
                  "type": "object",
                  "properties": {
                    "error": {
                      "type": "string"
                    }
                  }
                }
              }
            }
          }
        },
        "requestBody": {
          "content": {
            "application/json": {
              "schema": {
                "type": "object",
                "properties": {
                  "id_isla": {
                    "type": "integer"
                  },
                  "nombre": {
                    "type": "string"
                  }
                },
                "required": [
                  "id_isla"
                ]
              }
            }
          }
        }
      }
    },
    "/niveles/getByIsla/{id}": {
      "get": {
        "tags": [
          "Niveles"
        ],
        "description": "Endpoint para obtener los niveles por id de isla.",
        "parameters": [
          {
            "name": "id",
            "in": "path",
            "required": true,
            "schema": {
              "type": "string"
            },
            "description": "ID de la isla."
          }
        ],
        "responses": {
          "200": {
            "description": "Niveles obtenidos correctamente.",
            "content": {
              "application/json": {
                "schema": {
                  "type": "array",
                  "items": {
                    "type": "object",
                    "properties": {
                      "id_nivel": {
                        "type": "integer"
                      },
                      "id_isla": {
                        "type": "integer"
                      },
                      "nombre": {
                        "type": "string"
                      }
                    }
                  }
                }
              }
            }
          },
          "500": {
            "description": "Error al obtener los niveles.",
            "content": {
              "application/json": {
                "schema": {
                  "type": "object",
                  "properties": {
                    "error": {
                      "type": "string"
                    }
                  }
                }
              }
            }
          }
        }
      }
    },
    "/niveles/{id_nivel}": {
      "put": {
        "tags": [
          "Niveles"
        ],
        "description": "Endpoint para actualizar un nivel.",
        "parameters": [
          {
            "name": "id_nivel",
            "in": "path",
            "required": true,
            "schema": {
              "type": "string"
            },
            "description": "ID del nivel a actualizar."
          }
        ],
        "responses": {
          "200": {
            "description": "Nivel actualizado correctamente.",
            "content": {
              "application/json": {
                "schema": {
                  "type": "object",
                  "properties": {
                    "id_nivel": {
                      "type": "integer"
                    },
                    "id_isla": {
                      "type": "integer"
                    },
                    "nombre": {
                      "type": "string"
                    }
                  }
                }
              }
            }
          },
          "500": {
            "description": "Error al actualizar el nivel.",
            "content": {
              "application/json": {
                "schema": {
                  "type": "object",
                  "properties": {
                    "error": {
                      "type": "string"
                    }
                  }
                }
              }
            }
          }
        },
        "requestBody": {
          "content": {
            "application/json": {
              "schema": {
                "type": "object",
                "properties": {
                  "id_isla": {
                    "type": "integer"
                  },
                  "nombre": {
                    "type": "string"
                  }
                },
                "required": [
                  "id_isla",
                  "nombre"
                ]
              }
            }
          }
        }
      },
      "delete": {
        "tags": [
          "Niveles"
        ],
        "description": "Endpoint para eliminar un nivel.",
        "parameters": [
          {
            "name": "id_nivel",
            "in": "path",
            "required": true,
            "schema": {
              "type": "string"
            },
            "description": "ID del nivel a eliminar."
          }
        ],
        "responses": {
          "200": {
            "description": "Nivel eliminado correctamente.",
            "content": {
              "application/json": {
                "schema": {
                  "type": "object",
                  "properties": {
                    "id_nivel": {
                      "type": "integer"
                    },
                    "id_isla": {
                      "type": "integer"
                    },
                    "nombre": {
                      "type": "string"
                    }
                  }
                }
              }
            }
          },
          "500": {
            "description": "Error al eliminar el nivel.",
            "content": {
              "application/json": {
                "schema": {
                  "type": "object",
                  "properties": {
                    "error": {
                      "type": "string"
                    }
                  }
                }
              }
            }
          }
        }
      }
    },
    "/partesVideo/": {
      "get": {
        "description": "",
        "responses": {
          "200": {
            "description": "OK"
          },
          "500": {
            "description": "Internal Server Error"
          }
        }
      },
      "post": {
        "description": "",
        "responses": {
          "200": {
            "description": "OK"
          },
          "500": {
            "description": "Internal Server Error"
          }
        },
        "requestBody": {
          "content": {
            "application/json": {
              "schema": {
                "type": "object",
                "properties": {
                  "id_nivel": {
                    "example": "any"
                  },
                  "url_video": {
                    "example": "any"
                  },
                  "nombre": {
                    "example": "any"
                  }
                }
              }
            }
          }
        }
      }
    },
    "/partesVideo/getByNivel/{id}": {
      "get": {
        "description": "",
        "parameters": [
          {
            "name": "id",
            "in": "path",
            "required": true,
            "schema": {
              "type": "string"
            }
          }
        ],
        "responses": {
          "200": {
            "description": "OK"
          },
          "500": {
            "description": "Internal Server Error"
          }
        }
      }
    },
    "/partesVideo/{id}": {
      "get": {
        "description": "",
        "parameters": [
          {
            "name": "id",
            "in": "path",
            "required": true,
            "schema": {
              "type": "string"
            }
          }
        ],
        "responses": {
          "200": {
            "description": "OK"
          },
          "500": {
            "description": "Internal Server Error"
          }
        }
      },
      "delete": {
        "description": "",
        "parameters": [
          {
            "name": "id",
            "in": "path",
            "required": true,
            "schema": {
              "type": "string"
            }
          }
        ],
        "responses": {
          "200": {
            "description": "OK"
          },
          "500": {
            "description": "Internal Server Error"
          }
        },
        "requestBody": {
          "content": {
            "application/json": {
              "schema": {
                "type": "object",
                "properties": {
                  "id_nivel": {
                    "example": "any"
                  },
                  "url_video": {
                    "example": "any"
                  },
                  "nombre": {
                    "example": "any"
                  }
                }
              }
            }
          }
        }
      }
    },
    "/partesVideo/cambiarIndice/{id}": {
      "put": {
        "description": "",
        "parameters": [
          {
            "name": "id",
            "in": "path",
            "required": true,
            "schema": {
              "type": "string"
            }
          }
        ],
        "responses": {
          "200": {
            "description": "OK"
          },
          "404": {
            "description": "Not Found"
          },
          "500": {
            "description": "Internal Server Error"
          }
        },
        "requestBody": {
          "content": {
            "application/json": {
              "schema": {
                "type": "object",
                "properties": {
                  "direccion": {
                    "example": "any"
                  },
                  "id_nivel": {
                    "example": "any"
                  },
                  "url_video": {
                    "example": "any"
                  },
                  "nombre": {
                    "example": "any"
                  }
                }
              }
            }
          }
        }
      }
    }
  }
}